package.json
pypkg/__init__.py
pypkg/py.typed
p_y_p_k_g-0.0.8.dist-info/LICENSE
p_y_p_k_g-0.0.8.dist-info/METADATA
p_y_p_k_g-0.0.8.dist-info/WHEEL
p_y_p_k_g-0.0.8.dist-info/top_level.txt
p_y_p_k_g-0.0.8.dist-info/RECORD
